funapp/__init__.py
funapp/server/__init__.py
funapp/server/core.py
funapp/ui/login.py
funapp/work/__init__.py
funapp/work/quick.py
funapp-1.1.1.dist-info/METADATA
funapp-1.1.1.dist-info/WHEEL
funapp-1.1.1.dist-info/top_level.txt
funapp-1.1.1.dist-info/RECORD
