Metadata-Version: 2.4
Name: funapp
Version: 1.1.1
Summary: funapp
Author-email: 牛哥 <niuliangtao@qq.com>, farfarfun <farfarfun@qq.com>
Maintainer-email: 牛哥 <niuliangtao@qq.com>, farfarfun <farfarfun@qq.com>
Project-URL: Organization, https://github.com/farfarfun
Project-URL: Repository, https://github.com/farfarfun/funapp
Project-URL: Releases, https://github.com/farfarfun/funapp/releases
Requires-Python: >=3.8
